django_action_logger/__init__.py
django_action_logger/admin.py
django_action_logger/apps.py
django_action_logger/migrations/0001_initial.py
django_action_logger/migrations/__init__.py
django_action_logger/models.py
django_action_logger/signals.py
django_action_logger/templates/django_action_logger/djangoactionlogentry_list.html
django_action_logger/templates/django_action_logger/logentry.html
django_action_logger/templates/django_action_logger/logentrylist.html
django_action_logger/templatetags/django_action_logger.py
django_action_logger/tests.py
django_action_logger/urls.py
django_action_logger/views.py
django_action_logger-0.1.5.dist-info/METADATA
django_action_logger-0.1.5.dist-info/WHEEL
django_action_logger-0.1.5.dist-info/RECORD
